lcp_video/__init__.py
lcp_video/_version.py
lcp_video/analysis.py
lcp_video/audio.py
lcp_video/plotting.py
lcp_video/video.py
lcp_video/tests/__init__.py
lcp_video/tests/conftest.py
lcp_video/tests/test_examples.py
lcp_video/tests/test_video.py
lcp_video-0.0.0.dist-info/AUTHORS.rst
lcp_video-0.0.0.dist-info/LICENSE
lcp_video-0.0.0.dist-info/METADATA
lcp_video-0.0.0.dist-info/WHEEL
lcp_video-0.0.0.dist-info/entry_points.txt
lcp_video-0.0.0.dist-info/top_level.txt
lcp_video-0.0.0.dist-info/RECORD
