Metadata-Version: 2.1
Name: lcp-video
Version: 0.0.0
Summary: LCP video analysis
Home-page: https://github.com/vstadnytskyi/lcp-video
Author: Valentyn Stadnytskyi
Author-email: v.stadnytskyi@gmail.com
License: BSD (3-clause)
Platform: UNKNOWN
Classifier: Development Status :: 2 - Pre-Alpha
Classifier: Natural Language :: English
Classifier: Programming Language :: Python :: 3
Requires-Python: >=3.6
Requires-Dist: numpy
Requires-Dist: opencv-python
Requires-Dist: moviepy
Requires-Dist: scikit-image
Requires-Dist: matplotlib
Requires-Dist: librosa
